<?xml version="1.0" encoding="utf-8"?>
<LanguageData>

  <!-- Drone Resurrector Kit -->

  <ATR_DroneResurrectorKit.label>комплект реанимации дрона</ATR_DroneResurrectorKit.label>
  <ATR_DroneResurrectorKit.description>Специализированный комплект деталей и инструментов, способных реанимировать отключённого или повреждённого дрона. Комплект реанимации так же может реанимировать механических животных. Реанимированные дроны, должны полностью перезагрузиться, чтобы снова начать работу.</ATR_DroneResurrectorKit.description>
  <ATR_DroneResurrectorKit.comps.0.useLabel>Реанимировать дрона</ATR_DroneResurrectorKit.comps.0.useLabel>


  <!-- Android Resurrection Kit -->

  <ATR_AndroidResurrectorKit.label>комплект реанимации андроида</ATR_AndroidResurrectorKit.label>
  <ATR_AndroidResurrectorKit.description>Продвинутый специализированный комплект деталей и инструментов, способных реанимировать отключённого или повреждённого андроида. Продвинутый комплект реанимации может реанимировать любое механическое существо. Реанимированные андроиды, должны полностью перезагрузиться, чтобы снова начать работу.</ATR_AndroidResurrectorKit.description>
  <ATR_AndroidResurrectorKit.comps.0.useLabel>Реанимировать андроида</ATR_AndroidResurrectorKit.comps.0.useLabel>


</LanguageData>